{
    "academic_year": "2024/25",
    "type": 1,
    "date": "Friday, 25 April 2025",
    "location": "Oratory Church of St Wilfrid, York, North Yorkshire",
    "weight": "18-1-21 in F",
    "time": "",
    "changes": "1260",
    "method": "Plain Bob Doubles",
    "details": "",
    "ringers": [
        {
            "name": "Francesca R Lee (Alcuin)",
            "bell": "1"
        },
        {
            "name": "Phil Stokoe (Staff)",
            "bell": "2"
        },
        {
            "name": "Benjamin J Hartley (YSJ)",
            "bell": "3"
        },
        {
            "name": "Rosemary S Hall (Alcuin) (C)",
            "bell": "4"
        },
        {
            "name": "Suzanne E Timms (Alcuin)",
            "bell": "5"
        },
        {
            "name": "Alexander W Lister (Goodricke)",
            "bell": "6"
        }
    ],
    "footnotes": [
        "1st Quarter Peal: 6",
        "1st Quarter Peal on Treble: 1",
        "1st Quarter without simulated sound: 1",
        "25th Quarter Peal: 5",
        "Successfully organised his own first quarter after failed organisation by everyone else: 6",
        "With birthday compliments to Fran Lee (Treble)"
    ],
    "id": "1844748",
    "time_in_ms": 17455398
}